{
  "id": "recGTv6iSMJWYavI8",
  "title": "Sol-fa",
  "lessonSetName": "Sol-fa: Level 3",
  "subject": "Music",
  "gradeText": "GRADE(S): 4+",
  "sortId": "014.004.004.005",
  "rowType": "topic",
  "hasTopics": false,
  "isStandaloneCourse": false,
  "courseConnectionNames": [
    "Music: Level 3"
  ],
  "topicConnectionNames": [],
  "updatedAt": "2026-05-17T08:04:44.171Z",
  "terms": [
    {
      "termNumber": 1,
      "term": "Term 1",
      "weeks": [
        {
          "weekNumber": 1,
          "weekLabel": "Week 1",
          "lessons": [
            {
              "lessonId": "recw7Gw41vqgulm6v",
              "termNumber": 1,
              "termLabel": "Term 1",
              "weekNumber": 1,
              "weekLabel": "Week 1",
              "sequence": 1,
              "sort": 0,
              "lessonLabel": "Lesson 1",
              "title": "15m Sol-fa: Level 3 - Lesson 1",
              "anchor": "term-1-week-1-lesson-1",
              "links": [
                {
                  "text": "Warm-Ups (Video)",
                  "url": "https://vimeo.com/337660739/4bbc0a0711"
                },
                {
                  "text": "Warm-Ups (Audio)",
                  "url": "https://soundcloud.com/alveary/warm-up-form-2-and-3/s-cHDwD?in=alveary/sets/sol-fa-level-3"
                },
                {
                  "text": "Step 1",
                  "url": "https://vimeo.com/309000629/188f33d8c3"
                }
              ]
            }
          ]
        },
        {
          "weekNumber": 2,
          "weekLabel": "Week 2",
          "lessons": [
            {
              "lessonId": "rec1qBC7DrmgosZa6",
              "termNumber": 1,
              "termLabel": "Term 1",
              "weekNumber": 2,
              "weekLabel": "Week 2",
              "sequence": 2,
              "sort": 0,
              "lessonLabel": "Lesson 2",
              "title": "15m Sol-fa: Level 3 - Lesson 2",
              "anchor": "term-1-week-2-lesson-2",
              "links": [
                {
                  "text": "Warm-Ups (Video)",
                  "url": "https://vimeo.com/337660739/4bbc0a0711"
                },
                {
                  "text": "Warm-Ups (Audio)",
                  "url": "https://soundcloud.com/alveary/warm-up-form-2-and-3/s-cHDwD?in=alveary/sets/sol-fa-level-3"
                },
                {
                  "text": "Step 2",
                  "url": "https://soundcloud.com/alveary/step-2?in=alveary/sets/sol-fa-level-3"
                }
              ]
            }
          ]
        },
        {
          "weekNumber": 3,
          "weekLabel": "Week 3",
          "lessons": [
            {
              "lessonId": "recn4PeY5LQhvjQJN",
              "termNumber": 1,
              "termLabel": "Term 1",
              "weekNumber": 3,
              "weekLabel": "Week 3",
              "sequence": 3,
              "sort": 0,
              "lessonLabel": "Lesson 3",
              "title": "15m Sol-fa: Level 3 - Lesson 3",
              "anchor": "term-1-week-3-lesson-3",
              "links": [
                {
                  "text": "Warm-Ups (Video)",
                  "url": "https://vimeo.com/337660739/4bbc0a0711"
                },
                {
                  "text": "Warm-Ups (Audio)",
                  "url": "https://soundcloud.com/alveary/warm-up-form-2-and-3/s-cHDwD?in=alveary/sets/sol-fa-level-3"
                },
                {
                  "text": "Step 3",
                  "url": "https://soundcloud.com/alveary/step-3?in=alveary/sets/sol-fa-level-3"
                }
              ]
            }
          ]
        },
        {
          "weekNumber": 4,
          "weekLabel": "Week 4",
          "lessons": [
            {
              "lessonId": "recWRfPK43EEjLRIS",
              "termNumber": 1,
              "termLabel": "Term 1",
              "weekNumber": 4,
              "weekLabel": "Week 4",
              "sequence": 4,
              "sort": 0,
              "lessonLabel": "Lesson 4",
              "title": "15m Sol-fa: Level 3 - Lesson 4",
              "anchor": "term-1-week-4-lesson-4",
              "links": [
                {
                  "text": "Warm-Ups (Video)",
                  "url": "https://vimeo.com/337660739/4bbc0a0711"
                },
                {
                  "text": "Warm-Ups (Audio)",
                  "url": "https://soundcloud.com/alveary/warm-up-form-2-and-3/s-cHDwD?in=alveary/sets/sol-fa-level-3"
                },
                {
                  "text": "Step 4",
                  "url": "https://soundcloud.com/alveary/step-4?in=alveary/sets/sol-fa-level-3"
                }
              ]
            }
          ]
        },
        {
          "weekNumber": 5,
          "weekLabel": "Week 5",
          "lessons": [
            {
              "lessonId": "recHKYCCf6gOzUE0O",
              "termNumber": 1,
              "termLabel": "Term 1",
              "weekNumber": 5,
              "weekLabel": "Week 5",
              "sequence": 5,
              "sort": 0,
              "lessonLabel": "Lesson 5",
              "title": "15m Sol-fa: Level 3 - Lesson 5",
              "anchor": "term-1-week-5-lesson-5",
              "links": [
                {
                  "text": "Warm-Ups (Video)",
                  "url": "https://vimeo.com/337660739/4bbc0a0711"
                },
                {
                  "text": "Warm-Ups (Audio)",
                  "url": "https://soundcloud.com/alveary/warm-up-form-2-and-3/s-cHDwD?in=alveary/sets/sol-fa-level-3"
                },
                {
                  "text": "Step 5",
                  "url": "https://vimeo.com/311913089/e9a1f04a30"
                }
              ]
            }
          ]
        },
        {
          "weekNumber": 6,
          "weekLabel": "Week 6",
          "lessons": [
            {
              "lessonId": "reccJB1rqdbq3SJxB",
              "termNumber": 1,
              "termLabel": "Term 1",
              "weekNumber": 6,
              "weekLabel": "Week 6",
              "sequence": 6,
              "sort": 0,
              "lessonLabel": "Lesson 6",
              "title": "15m Sol-fa: Level 3 - Lesson 6",
              "anchor": "term-1-week-6-lesson-6",
              "links": [
                {
                  "text": "Warm-Ups (Video)",
                  "url": "https://vimeo.com/337660739/4bbc0a0711"
                },
                {
                  "text": "Warm-Ups (Audio)",
                  "url": "https://soundcloud.com/alveary/warm-up-form-2-and-3/s-cHDwD?in=alveary/sets/sol-fa-level-3"
                },
                {
                  "text": "Step 6",
                  "url": "https://soundcloud.com/alveary/step-6?in=alveary/sets/sol-fa-level-3"
                }
              ]
            }
          ]
        },
        {
          "weekNumber": 7,
          "weekLabel": "Week 7",
          "lessons": [
            {
              "lessonId": "reccOMUACLAqZp4lb",
              "termNumber": 1,
              "termLabel": "Term 1",
              "weekNumber": 7,
              "weekLabel": "Week 7",
              "sequence": 7,
              "sort": 0,
              "lessonLabel": "Lesson 7",
              "title": "15m Sol-fa: Level 3 - Lesson 7",
              "anchor": "term-1-week-7-lesson-7",
              "links": [
                {
                  "text": "Warm-Ups (Video)",
                  "url": "https://vimeo.com/337660739/4bbc0a0711"
                },
                {
                  "text": "Warm-Ups (Audio)",
                  "url": "https://soundcloud.com/alveary/warm-up-form-2-and-3/s-cHDwD?in=alveary/sets/sol-fa-level-3"
                },
                {
                  "text": "Step 7a",
                  "url": "https://soundcloud.com/alveary/step-7a?in=alveary/sets/sol-fa-level-3"
                }
              ]
            }
          ]
        },
        {
          "weekNumber": 8,
          "weekLabel": "Week 8",
          "lessons": [
            {
              "lessonId": "reclojqlseglF69zR",
              "termNumber": 1,
              "termLabel": "Term 1",
              "weekNumber": 8,
              "weekLabel": "Week 8",
              "sequence": 8,
              "sort": 0,
              "lessonLabel": "Lesson 8",
              "title": "15m Sol-fa: Level 3 - Lesson 8",
              "anchor": "term-1-week-8-lesson-8",
              "links": [
                {
                  "text": "Warm-Ups (Video)",
                  "url": "https://vimeo.com/337660739/4bbc0a0711"
                },
                {
                  "text": "Warm-Ups (Audio)",
                  "url": "https://soundcloud.com/alveary/warm-up-form-2-and-3/s-cHDwD?in=alveary/sets/sol-fa-level-3"
                },
                {
                  "text": "Step 7b",
                  "url": "https://soundcloud.com/alveary/step-8?in=alveary/sets/sol-fa-level-3"
                }
              ]
            }
          ]
        },
        {
          "weekNumber": 9,
          "weekLabel": "Week 9",
          "lessons": [
            {
              "lessonId": "rec9zzYGe8OSkkrfW",
              "termNumber": 1,
              "termLabel": "Term 1",
              "weekNumber": 9,
              "weekLabel": "Week 9",
              "sequence": 9,
              "sort": 0,
              "lessonLabel": "Lesson 9",
              "title": "15m Sol-fa: Level 3 - Lesson 9",
              "anchor": "term-1-week-9-lesson-9",
              "links": [
                {
                  "text": "Warm-Ups (Video)",
                  "url": "https://vimeo.com/337660739/4bbc0a0711"
                },
                {
                  "text": "Warm-Ups (Audio)",
                  "url": "https://soundcloud.com/alveary/warm-up-form-2-and-3/s-cHDwD?in=alveary/sets/sol-fa-level-3"
                },
                {
                  "text": "Step 7c",
                  "url": "https://soundcloud.com/alveary/step-9?in=alveary/sets/sol-fa-level-3"
                }
              ]
            }
          ]
        },
        {
          "weekNumber": 10,
          "weekLabel": "Week 10",
          "lessons": [
            {
              "lessonId": "recOVQzlR7ZyRBegw",
              "termNumber": 1,
              "termLabel": "Term 1",
              "weekNumber": 10,
              "weekLabel": "Week 10",
              "sequence": 10,
              "sort": 0,
              "lessonLabel": "Lesson 10",
              "title": "15m Sol-fa: Level 3 - Lesson 10",
              "anchor": "term-1-week-10-lesson-10",
              "links": [
                {
                  "text": "Warm-Ups (Video)",
                  "url": "https://vimeo.com/337660739/4bbc0a0711"
                },
                {
                  "text": "Warm-Ups (Audio)",
                  "url": "https://soundcloud.com/alveary/warm-up-form-2-and-3/s-cHDwD?in=alveary/sets/sol-fa-level-3"
                },
                {
                  "text": "Step 7d",
                  "url": "https://soundcloud.com/alveary/step-10?in=alveary/sets/sol-fa-level-3&utm_source=clipboard&utm_medium=text&utm_campaign=social_sharing"
                },
                {
                  "text": "Step 7d in C Answer Key",
                  "url": "https://soundcloud.com/alveary/7e-in-c-2019?in=alveary/sets/sol-fa-level-3"
                }
              ]
            }
          ]
        },
        {
          "weekNumber": 11,
          "weekLabel": "Week 11",
          "lessons": [
            {
              "lessonId": "rec0AzZiV4qkdgU0F",
              "termNumber": 1,
              "termLabel": "Term 1",
              "weekNumber": 11,
              "weekLabel": "Week 11",
              "sequence": 11,
              "sort": 0,
              "lessonLabel": "Lesson 11",
              "title": "15m Sol-fa: Level 3 - Lesson 11",
              "anchor": "term-1-week-11-lesson-11",
              "links": [
                {
                  "text": "Warm-Ups (Video)",
                  "url": "https://vimeo.com/337660739/4bbc0a0711"
                },
                {
                  "text": "Warm-Ups (Audio)",
                  "url": "https://soundcloud.com/alveary/warm-up-form-2-and-3/s-cHDwD?in=alveary/sets/sol-fa-level-3"
                },
                {
                  "text": "Step 7e",
                  "url": "https://soundcloud.com/alveary/step-11?in=alveary/sets/sol-fa-level-3"
                },
                {
                  "text": "Step 7e in D Answer Key",
                  "url": "https://soundcloud.com/alveary/7e-in-d-2019?in=alveary/sets/sol-fa-level-3"
                },
                {
                  "text": "Step 7e in F Answer Key",
                  "url": "https://soundcloud.com/alveary/7e-in-f-2019?in=alveary/sets/sol-fa-level-3"
                }
              ]
            }
          ]
        }
      ]
    },
    {
      "termNumber": 2,
      "term": "Term 2",
      "weeks": [
        {
          "weekNumber": 13,
          "weekLabel": "Week 1",
          "lessons": [
            {
              "lessonId": "recCGBy6QZyzGkCZK",
              "termNumber": 2,
              "termLabel": "Term 2",
              "weekNumber": 13,
              "weekLabel": "Week 1",
              "sequence": 13,
              "sort": 0,
              "lessonLabel": "Lesson 13",
              "title": "15m Sol-fa: Level 3 - Lesson 13",
              "anchor": "term-2-week-13-lesson-13",
              "links": [
                {
                  "text": "Warm-Ups (Video)",
                  "url": "https://vimeo.com/337660739/4bbc0a0711"
                },
                {
                  "text": "Warm-Ups (Audio)",
                  "url": "https://soundcloud.com/alveary/warm-up-form-2-and-3/s-cHDwD?in=alveary/sets/sol-fa-level-3"
                },
                {
                  "text": "Step 8",
                  "url": "https://soundcloud.com/alveary/term-2-step-1?in=alveary/sets/sol-fa-level-3"
                },
                {
                  "text": "Step 8 Answer Key",
                  "url": "https://soundcloud.com/alveary/step-8-answer-key?in=alveary/sets/sol-fa-level-3&utm_source=clipboard&utm_medium=text&utm_campaign=social_sharing"
                }
              ]
            }
          ]
        },
        {
          "weekNumber": 14,
          "weekLabel": "Week 2",
          "lessons": [
            {
              "lessonId": "rec657PFPsbbW38oK",
              "termNumber": 2,
              "termLabel": "Term 2",
              "weekNumber": 14,
              "weekLabel": "Week 2",
              "sequence": 14,
              "sort": 0,
              "lessonLabel": "Lesson 14",
              "title": "15m Sol-fa: Level 3 - Lesson 14",
              "anchor": "term-2-week-14-lesson-14",
              "links": [
                {
                  "text": "Warm-Ups (Video)",
                  "url": "https://vimeo.com/337660739/4bbc0a0711"
                },
                {
                  "text": "Warm-Ups (Audio)",
                  "url": "https://soundcloud.com/alveary/warm-up-form-2-and-3/s-cHDwD?in=alveary/sets/sol-fa-level-3"
                },
                {
                  "text": "Step 9",
                  "url": "https://soundcloud.com/alveary/term-2-step-2?in=alveary/sets/sol-fa-level-3"
                },
                {
                  "text": "Step 9 Answer Key",
                  "url": "https://soundcloud.com/alveary/step-9-answer-key?in=alveary/sets/sol-fa-level-3&utm_source=clipboard&utm_medium=text&utm_campaign=social_sharing"
                }
              ]
            }
          ]
        },
        {
          "weekNumber": 15,
          "weekLabel": "Week 3",
          "lessons": [
            {
              "lessonId": "rec6E6wHtpeed04Gt",
              "termNumber": 2,
              "termLabel": "Term 2",
              "weekNumber": 15,
              "weekLabel": "Week 3",
              "sequence": 15,
              "sort": 0,
              "lessonLabel": "Lesson 15",
              "title": "15m Sol-fa: Level 3 - Lesson 15",
              "anchor": "term-2-week-15-lesson-15",
              "links": [
                {
                  "text": "Warm-Ups (Video)",
                  "url": "https://vimeo.com/337660739/4bbc0a0711"
                },
                {
                  "text": "Warm-Ups (Audio)",
                  "url": "https://soundcloud.com/alveary/warm-up-form-2-and-3/s-cHDwD?in=alveary/sets/sol-fa-level-3"
                },
                {
                  "text": "Step 10a",
                  "url": "https://soundcloud.com/alveary/term-2-step-10a?in=alveary/sets/sol-fa-level-3"
                }
              ]
            }
          ]
        },
        {
          "weekNumber": 16,
          "weekLabel": "Week 4",
          "lessons": [
            {
              "lessonId": "recJ2HxKPaIuAdJ96",
              "termNumber": 2,
              "termLabel": "Term 2",
              "weekNumber": 16,
              "weekLabel": "Week 4",
              "sequence": 16,
              "sort": 0,
              "lessonLabel": "Lesson 16",
              "title": "15m Sol-fa: Level 3 - Lesson 16",
              "anchor": "term-2-week-16-lesson-16",
              "links": [
                {
                  "text": "Warm-Ups (Video)",
                  "url": "https://vimeo.com/337660739/4bbc0a0711"
                },
                {
                  "text": "Warm-Ups (Audio)",
                  "url": "https://soundcloud.com/alveary/warm-up-form-2-and-3/s-cHDwD?in=alveary/sets/sol-fa-level-3"
                },
                {
                  "text": "Step 10b",
                  "url": "https://soundcloud.com/alveary/term-2-step-10b?in=alveary/sets/sol-fa-level-3"
                }
              ]
            }
          ]
        },
        {
          "weekNumber": 17,
          "weekLabel": "Week 5",
          "lessons": [
            {
              "lessonId": "recYOha72GdllfqKB",
              "termNumber": 2,
              "termLabel": "Term 2",
              "weekNumber": 17,
              "weekLabel": "Week 5",
              "sequence": 17,
              "sort": 0,
              "lessonLabel": "Lesson 17",
              "title": "15m Sol-fa: Level 3 - Lesson 17",
              "anchor": "term-2-week-17-lesson-17",
              "links": [
                {
                  "text": "Warm-Ups (Video)",
                  "url": "https://vimeo.com/337660739/4bbc0a0711"
                },
                {
                  "text": "Warm-Ups (Audio)",
                  "url": "https://soundcloud.com/alveary/warm-up-form-2-and-3/s-cHDwD?in=alveary/sets/sol-fa-level-3"
                },
                {
                  "text": "Step 11a",
                  "url": "https://soundcloud.com/alveary/step-11a?in=alveary/sets/sol-fa-level-3"
                },
                {
                  "text": "Sol-fa Ladder",
                  "url": "https://drive.google.com/file/d/1xbqjj0EvQz1mVjAON0i6QmCP3mPQaL_U/view?usp=drive_link"
                },
                {
                  "text": "Reading Sol-fa Shorthand",
                  "url": "https://drive.google.com/file/d/1tLWKUzqNeLiRvbE7tIa4N9zynUMz9XbO/view?usp=drive_link"
                }
              ]
            }
          ]
        },
        {
          "weekNumber": 18,
          "weekLabel": "Week 6",
          "lessons": [
            {
              "lessonId": "recZX06pvVlRNJEjT",
              "termNumber": 2,
              "termLabel": "Term 2",
              "weekNumber": 18,
              "weekLabel": "Week 6",
              "sequence": 18,
              "sort": 0,
              "lessonLabel": "Lesson 18",
              "title": "15m Sol-fa: Level 3 - Lesson 18",
              "anchor": "term-2-week-18-lesson-18",
              "links": [
                {
                  "text": "Warm-Ups (Video)",
                  "url": "https://vimeo.com/337660739/4bbc0a0711"
                },
                {
                  "text": "Warm-Ups (Audio)",
                  "url": "https://soundcloud.com/alveary/warm-up-form-2-and-3/s-cHDwD?in=alveary/sets/sol-fa-level-3"
                },
                {
                  "text": "Step 11b",
                  "url": "https://soundcloud.com/alveary/step-11b?in=alveary/sets/sol-fa-level-3&utm_source=clipboard&utm_medium=text&utm_campaign=social_sharing"
                },
                {
                  "text": "Step 11b Answer Key",
                  "url": "https://soundcloud.com/alveary/step-11b-answer-key?in=alveary/sets/sol-fa-level-3&utm_source=clipboard&utm_medium=text&utm_campaign=social_sharing"
                },
                {
                  "text": "Reading Sol-fa Shorthand",
                  "url": "https://charlottemasoninstitute.org/Member-PDFs/Alveary/Curriculum-Supplements/Music/Solfege/Step-11-FiftyStepsinSight-Singingp.8.pdf"
                }
              ]
            }
          ]
        },
        {
          "weekNumber": 19,
          "weekLabel": "Week 7",
          "lessons": [
            {
              "lessonId": "rec88NgHY4SrHeiWh",
              "termNumber": 2,
              "termLabel": "Term 2",
              "weekNumber": 19,
              "weekLabel": "Week 7",
              "sequence": 19,
              "sort": 0,
              "lessonLabel": "Lesson 19",
              "title": "15m Sol-fa: Level 3 - Lesson 19",
              "anchor": "term-2-week-19-lesson-19",
              "links": [
                {
                  "text": "Warm-Ups (Video)",
                  "url": "https://vimeo.com/337660739/4bbc0a0711"
                },
                {
                  "text": "Warm-Ups (Audio)",
                  "url": "https://soundcloud.com/alveary/warm-up-form-2-and-3/s-cHDwD?in=alveary/sets/sol-fa-level-3"
                },
                {
                  "text": "Step 11c",
                  "url": "https://soundcloud.com/alveary/step-11c?in=alveary/sets/sol-fa-level-3"
                },
                {
                  "text": "Step 11c Answer Key",
                  "url": "https://soundcloud.com/alveary/step-11c-answer-key?in=alveary/sets/sol-fa-level-3&utm_source=clipboard&utm_medium=text&utm_campaign=social_sharing"
                }
              ]
            }
          ]
        },
        {
          "weekNumber": 20,
          "weekLabel": "Week 8",
          "lessons": [
            {
              "lessonId": "reckLN8dTVEAL0OEY",
              "termNumber": 2,
              "termLabel": "Term 2",
              "weekNumber": 20,
              "weekLabel": "Week 8",
              "sequence": 20,
              "sort": 0,
              "lessonLabel": "Lesson 20",
              "title": "15m Sol-fa: Level 3 - Lesson 20",
              "anchor": "term-2-week-20-lesson-20",
              "links": [
                {
                  "text": "Warm-Ups (Video)",
                  "url": "https://vimeo.com/337660739/4bbc0a0711"
                },
                {
                  "text": "Warm-Ups (Audio)",
                  "url": "https://soundcloud.com/alveary/warm-up-form-2-and-3/s-cHDwD?in=alveary/sets/sol-fa-level-3"
                },
                {
                  "text": "Step 11d",
                  "url": "https://soundcloud.com/alveary/step-11d?in=alveary/sets/sol-fa-level-3"
                },
                {
                  "text": "Step 11d Answer Key",
                  "url": "https://soundcloud.com/alveary/step-11d-answer-key?in=alveary/sets/sol-fa-level-3&utm_source=clipboard&utm_medium=text&utm_campaign=social_sharing"
                }
              ]
            }
          ]
        },
        {
          "weekNumber": 21,
          "weekLabel": "Week 9",
          "lessons": [
            {
              "lessonId": "recSC1oCyf1FD69yk",
              "termNumber": 2,
              "termLabel": "Term 2",
              "weekNumber": 21,
              "weekLabel": "Week 9",
              "sequence": 21,
              "sort": 0,
              "lessonLabel": "Lesson 21",
              "title": "15m Sol-fa: Level 3 - Lesson 21",
              "anchor": "term-2-week-21-lesson-21",
              "links": [
                {
                  "text": "Warm-Ups (Video)",
                  "url": "https://vimeo.com/337660739/4bbc0a0711"
                },
                {
                  "text": "Warm-Ups (Audio)",
                  "url": "https://soundcloud.com/alveary/warm-up-form-2-and-3/s-cHDwD?in=alveary/sets/sol-fa-level-3"
                },
                {
                  "text": "Step 11e",
                  "url": "https://soundcloud.com/alveary/step-11e?in=alveary/sets/sol-fa-level-3"
                },
                {
                  "text": "Step 11e Answer Key",
                  "url": "https://soundcloud.com/alveary/step-11e-answer-key?in=alveary/sets/sol-fa-level-3"
                }
              ]
            }
          ]
        },
        {
          "weekNumber": 22,
          "weekLabel": "Week 10",
          "lessons": [
            {
              "lessonId": "recKQ3gAWaDrcdnAB",
              "termNumber": 2,
              "termLabel": "Term 2",
              "weekNumber": 22,
              "weekLabel": "Week 10",
              "sequence": 22,
              "sort": 0,
              "lessonLabel": "Lesson 22",
              "title": "15m Sol-fa: Level 3 - Lesson 22",
              "anchor": "term-2-week-22-lesson-22",
              "links": [
                {
                  "text": "Warm-Ups (Video)",
                  "url": "https://vimeo.com/337660739/4bbc0a0711"
                },
                {
                  "text": "Warm-Ups (Audio)",
                  "url": "https://soundcloud.com/alveary/warm-up-form-2-and-3/s-cHDwD?in=alveary/sets/sol-fa-level-3"
                },
                {
                  "text": "Step 12a",
                  "url": "https://soundcloud.com/alveary/step-12a?in=alveary/sets/sol-fa-level-3"
                },
                {
                  "text": "Step 12 Answer Key",
                  "url": "https://soundcloud.com/alveary/step-12-answer-key?in=alveary/sets/sol-fa-level-3&utm_source=clipboard&utm_medium=text&utm_campaign=social_sharing"
                }
              ]
            }
          ]
        },
        {
          "weekNumber": 23,
          "weekLabel": "Week 11",
          "lessons": [
            {
              "lessonId": "recGDXk0heoEgyCxc",
              "termNumber": 2,
              "termLabel": "Term 2",
              "weekNumber": 23,
              "weekLabel": "Week 11",
              "sequence": 23,
              "sort": 0,
              "lessonLabel": "Lesson 23",
              "title": "15m Sol-fa: Level 3 - Lesson 23",
              "anchor": "term-2-week-23-lesson-23",
              "links": [
                {
                  "text": "Warm-Ups (Video)",
                  "url": "https://vimeo.com/337660739/4bbc0a0711"
                },
                {
                  "text": "Warm-Ups (Audio)",
                  "url": "https://soundcloud.com/alveary/warm-up-form-2-and-3/s-cHDwD?in=alveary/sets/sol-fa-level-3"
                },
                {
                  "text": "Step 12b",
                  "url": "https://soundcloud.com/alveary/step-12b?in=alveary/sets/sol-fa-level-3"
                },
                {
                  "text": "Step 12 Answer Key",
                  "url": "https://soundcloud.com/alveary/step-12-answer-key?in=alveary/sets/sol-fa-level-3&utm_source=clipboard&utm_medium=text&utm_campaign=social_sharing"
                }
              ]
            }
          ]
        }
      ]
    },
    {
      "termNumber": 3,
      "term": "Term 3",
      "weeks": [
        {
          "weekNumber": 25,
          "weekLabel": "Week 1",
          "lessons": [
            {
              "lessonId": "reckra7AAYIpy4lg3",
              "termNumber": 3,
              "termLabel": "Term 3",
              "weekNumber": 25,
              "weekLabel": "Week 1",
              "sequence": 25,
              "sort": 0,
              "lessonLabel": "Lesson 25",
              "title": "15m Sol-fa: Level 3 - Lesson 25",
              "anchor": "term-3-week-25-lesson-25",
              "links": [
                {
                  "text": "Warm-Ups (Video)",
                  "url": "https://vimeo.com/337660739/4bbc0a0711"
                },
                {
                  "text": "Warm-Ups (Audio)",
                  "url": "https://soundcloud.com/alveary/warm-up-form-2-and-3/s-cHDwD?in=alveary/sets/sol-fa-level-3"
                },
                {
                  "text": "Step 13a",
                  "url": "https://soundcloud.com/alveary/term-3-step-13a?in=alveary/sets/sol-fa-level-3"
                },
                {
                  "text": "Step 13a Answer Key",
                  "url": "https://soundcloud.com/alveary/step-13a-answer-key?in=alveary/sets/sol-fa-level-3&utm_source=clipboard&utm_medium=text&utm_campaign=social_sharing"
                }
              ]
            }
          ]
        },
        {
          "weekNumber": 26,
          "weekLabel": "Week 2",
          "lessons": [
            {
              "lessonId": "recDl58DxfL3OGgI4",
              "termNumber": 3,
              "termLabel": "Term 3",
              "weekNumber": 26,
              "weekLabel": "Week 2",
              "sequence": 26,
              "sort": 0,
              "lessonLabel": "Lesson 26",
              "title": "15m Sol-fa: Level 3 - Lesson 26",
              "anchor": "term-3-week-26-lesson-26",
              "links": [
                {
                  "text": "Warm-Ups (Video)",
                  "url": "https://vimeo.com/337660739/4bbc0a0711"
                },
                {
                  "text": "Warm-Ups (Audio)",
                  "url": "https://soundcloud.com/alveary/warm-up-form-2-and-3/s-cHDwD?in=alveary/sets/sol-fa-level-3"
                },
                {
                  "text": "Step 13b",
                  "url": "https://soundcloud.com/alveary/term-3-step-13b?in=alveary/sets/sol-fa-level-3"
                },
                {
                  "text": "Step 13b Answer Key",
                  "url": "https://soundcloud.com/alveary/step-13b-answer-key?in=alveary/sets/sol-fa-level-3&utm_source=clipboard&utm_medium=text&utm_campaign=social_sharing"
                }
              ]
            }
          ]
        },
        {
          "weekNumber": 27,
          "weekLabel": "Week 3",
          "lessons": [
            {
              "lessonId": "recPCLSWc9TBW7SDM",
              "termNumber": 3,
              "termLabel": "Term 3",
              "weekNumber": 27,
              "weekLabel": "Week 3",
              "sequence": 27,
              "sort": 0,
              "lessonLabel": "Lesson 27",
              "title": "15m Sol-fa: Level 3 - Lesson 27",
              "anchor": "term-3-week-27-lesson-27",
              "links": [
                {
                  "text": "Warm-Ups (Video)",
                  "url": "https://vimeo.com/337660739/4bbc0a0711"
                },
                {
                  "text": "Warm-Ups (Audio)",
                  "url": "https://soundcloud.com/alveary/warm-up-form-2-and-3/s-cHDwD?in=alveary/sets/sol-fa-level-3"
                },
                {
                  "text": "Step 13c Ear Tests and Answer Key",
                  "url": "https://soundcloud.com/alveary/step-13c-ear-tests-and-answer?in=alveary/sets/sol-fa-level-3"
                }
              ]
            }
          ]
        },
        {
          "weekNumber": 28,
          "weekLabel": "Week 4",
          "lessons": [
            {
              "lessonId": "recgaaJclgdAJqVRh",
              "termNumber": 3,
              "termLabel": "Term 3",
              "weekNumber": 28,
              "weekLabel": "Week 4",
              "sequence": 28,
              "sort": 0,
              "lessonLabel": "Lesson 28",
              "title": "15m Sol-fa: Level 3 - Lesson 28",
              "anchor": "term-3-week-28-lesson-28",
              "links": [
                {
                  "text": "Warm-Ups (Video)",
                  "url": "https://vimeo.com/337660739/4bbc0a0711"
                },
                {
                  "text": "Warm-Ups (Audio)",
                  "url": "https://soundcloud.com/alveary/warm-up-form-2-and-3/s-cHDwD?in=alveary/sets/sol-fa-level-3"
                },
                {
                  "text": "Step 13d",
                  "url": "https://soundcloud.com/alveary/step-13d?in=alveary/sets/sol-fa-level-3"
                }
              ]
            }
          ]
        },
        {
          "weekNumber": 29,
          "weekLabel": "Week 5",
          "lessons": [
            {
              "lessonId": "recAq2AG8RlPix941",
              "termNumber": 3,
              "termLabel": "Term 3",
              "weekNumber": 29,
              "weekLabel": "Week 5",
              "sequence": 29,
              "sort": 0,
              "lessonLabel": "Lesson 29",
              "title": "15m Sol-fa: Level 3 - Lesson 29",
              "anchor": "term-3-week-29-lesson-29",
              "links": [
                {
                  "text": "Warm-Ups (Video)",
                  "url": "https://vimeo.com/337660739/4bbc0a0711"
                },
                {
                  "text": "Warm-Ups (Audio)",
                  "url": "https://soundcloud.com/alveary/warm-up-form-2-and-3/s-cHDwD?in=alveary/sets/sol-fa-level-3"
                },
                {
                  "text": "Step 13e Answer Key",
                  "url": "https://soundcloud.com/alveary/step-13e-answer-key?in=alveary/sets/sol-fa-level-3&utm_source=clipboard&utm_medium=text&utm_campaign=social_sharing"
                }
              ]
            }
          ]
        },
        {
          "weekNumber": 30,
          "weekLabel": "Week 6",
          "lessons": [
            {
              "lessonId": "recJ43psIGTC3N6Oh",
              "termNumber": 3,
              "termLabel": "Term 3",
              "weekNumber": 30,
              "weekLabel": "Week 6",
              "sequence": 30,
              "sort": 0,
              "lessonLabel": "Lesson 30",
              "title": "15m Sol-fa: Level 3 - Lesson 30",
              "anchor": "term-3-week-30-lesson-30",
              "links": [
                {
                  "text": "Warm-Ups (Video)",
                  "url": "https://vimeo.com/337660739/4bbc0a0711"
                },
                {
                  "text": "Warm-Ups (Audio)",
                  "url": "https://soundcloud.com/alveary/warm-up-form-2-and-3/s-cHDwD?in=alveary/sets/sol-fa-level-3"
                },
                {
                  "text": "Step 13f Ear Tests and Answer Key",
                  "url": "https://soundcloud.com/alveary/step-13f-ear-tests-and-answer?in=alveary/sets/sol-fa-level-3"
                }
              ]
            }
          ]
        },
        {
          "weekNumber": 31,
          "weekLabel": "Week 7",
          "lessons": [
            {
              "lessonId": "recRq8GJjrx9zt6Ja",
              "termNumber": 3,
              "termLabel": "Term 3",
              "weekNumber": 31,
              "weekLabel": "Week 7",
              "sequence": 31,
              "sort": 0,
              "lessonLabel": "Lesson 31",
              "title": "15m Sol-fa: Level 3 - Lesson 31",
              "anchor": "term-3-week-31-lesson-31",
              "links": [
                {
                  "text": "Warm-Ups (Video)",
                  "url": "https://vimeo.com/337660739/4bbc0a0711"
                },
                {
                  "text": "Warm-Ups (Audio)",
                  "url": "https://soundcloud.com/alveary/warm-up-form-2-and-3/s-cHDwD?in=alveary/sets/sol-fa-level-3"
                },
                {
                  "text": "Step 13g",
                  "url": "https://soundcloud.com/alveary/step-13g?in=alveary/sets/sol-fa-level-3"
                }
              ]
            }
          ]
        },
        {
          "weekNumber": 32,
          "weekLabel": "Week 8",
          "lessons": [
            {
              "lessonId": "recrm6o3A3WL03LUA",
              "termNumber": 3,
              "termLabel": "Term 3",
              "weekNumber": 32,
              "weekLabel": "Week 8",
              "sequence": 32,
              "sort": 0,
              "lessonLabel": "Lesson 32",
              "title": "15m Sol-fa: Level 3 - Lesson 32",
              "anchor": "term-3-week-32-lesson-32",
              "links": [
                {
                  "text": "Warm-Ups (Video)",
                  "url": "https://vimeo.com/337660739/4bbc0a0711"
                },
                {
                  "text": "Warm-Ups (Audio)",
                  "url": "https://soundcloud.com/alveary/warm-up-form-2-and-3/s-cHDwD?in=alveary/sets/sol-fa-level-3"
                },
                {
                  "text": "Step 13h",
                  "url": "https://soundcloud.com/alveary/step-13h?in=alveary/sets/sol-fa-level-3"
                }
              ]
            }
          ]
        },
        {
          "weekNumber": 33,
          "weekLabel": "Week 9",
          "lessons": [
            {
              "lessonId": "reccGzY1BSCvfbGIx",
              "termNumber": 3,
              "termLabel": "Term 3",
              "weekNumber": 33,
              "weekLabel": "Week 9",
              "sequence": 33,
              "sort": 0,
              "lessonLabel": "Lesson 33",
              "title": "15m Sol-fa: Level 3 - Lesson 33",
              "anchor": "term-3-week-33-lesson-33",
              "links": [
                {
                  "text": "Warm-Ups (Video)",
                  "url": "https://vimeo.com/337660739/4bbc0a0711"
                },
                {
                  "text": "Warm-Ups (Audio)",
                  "url": "https://soundcloud.com/alveary/warm-up-form-2-and-3/s-cHDwD?in=alveary/sets/sol-fa-level-3"
                },
                {
                  "text": "Step 14a",
                  "url": "https://soundcloud.com/alveary/step-14a?in=alveary/sets/sol-fa-level-3"
                }
              ]
            }
          ]
        },
        {
          "weekNumber": 34,
          "weekLabel": "Week 10",
          "lessons": [
            {
              "lessonId": "recfguyX9uxpfpEMf",
              "termNumber": 3,
              "termLabel": "Term 3",
              "weekNumber": 34,
              "weekLabel": "Week 10",
              "sequence": 34,
              "sort": 0,
              "lessonLabel": "Lesson 34",
              "title": "15m Sol-fa: Level 3 - Lesson 34",
              "anchor": "term-3-week-34-lesson-34",
              "links": [
                {
                  "text": "Warm-Ups (Video)",
                  "url": "https://vimeo.com/337660739/4bbc0a0711"
                },
                {
                  "text": "Warm-Ups (Audio)",
                  "url": "https://soundcloud.com/alveary/warm-up-form-2-and-3/s-cHDwD?in=alveary/sets/sol-fa-level-3"
                },
                {
                  "text": "Step 14b",
                  "url": "https://soundcloud.com/alveary/step-14b?in=alveary/sets/sol-fa-level-3"
                },
                {
                  "text": "Step 14b-c Answer Key",
                  "url": "https://soundcloud.com/alveary/step-14b-c-answer-key?in=alveary/sets/sol-fa-level-3&utm_source=clipboard&utm_medium=text&utm_campaign=social_sharing"
                }
              ]
            }
          ]
        },
        {
          "weekNumber": 35,
          "weekLabel": "Week 11",
          "lessons": [
            {
              "lessonId": "reca6DK58udFvBM8u",
              "termNumber": 3,
              "termLabel": "Term 3",
              "weekNumber": 35,
              "weekLabel": "Week 11",
              "sequence": 35,
              "sort": 0,
              "lessonLabel": "Lesson 35",
              "title": "15m Sol-fa: Level 3 - Lesson 35",
              "anchor": "term-3-week-35-lesson-35",
              "links": [
                {
                  "text": "Warm-Ups (Video)",
                  "url": "https://vimeo.com/337660739/4bbc0a0711"
                },
                {
                  "text": "Warm-Ups (Audio)",
                  "url": "https://soundcloud.com/alveary/warm-up-form-2-and-3/s-cHDwD?in=alveary/sets/sol-fa-level-3"
                },
                {
                  "text": "Step 14c",
                  "url": "https://soundcloud.com/alveary/step-14c?in=alveary/sets/sol-fa-level-3"
                },
                {
                  "text": "Step 14b-c Answer Key",
                  "url": "https://soundcloud.com/alveary/step-14b-c-answer-key?in=alveary/sets/sol-fa-level-3&utm_source=clipboard&utm_medium=text&utm_campaign=social_sharing"
                }
              ]
            }
          ]
        }
      ]
    }
  ]
}
